sphinx_confluencebuilder_extras/__init__.py
sphinx_confluencebuilder_extras/mermaid_patch.py
sphinx_confluencebuilder_extras/pageproperties.py
sphinx_confluencebuilder_extras/skeleton.py
sphinx_confluencebuilder_extras/storage_format.py
sphinx_confluencebuilder_extras-0.0.2.dist-info/AUTHORS.rst
sphinx_confluencebuilder_extras-0.0.2.dist-info/LICENSE.txt
sphinx_confluencebuilder_extras-0.0.2.dist-info/METADATA
sphinx_confluencebuilder_extras-0.0.2.dist-info/WHEEL
sphinx_confluencebuilder_extras-0.0.2.dist-info/top_level.txt
sphinx_confluencebuilder_extras-0.0.2.dist-info/RECORD
