Metadata-Version: 2.1
Name: sphinx-confluencebuilder-extras
Version: 0.0.2
Summary: Add a short description here!
Home-page: https://github.com/pyscaffold/pyscaffold/
Author: lmonson
Author-email: lmonson@computer.org
License: MIT
Project-URL: Documentation, https://pyscaffold.org/
Platform: any
Classifier: Development Status :: 4 - Beta
Classifier: Programming Language :: Python
License-File: LICENSE.txt
License-File: AUTHORS.rst
Requires-Dist: importlib-metadata
Requires-Dist: python-version (>="3.9")
Requires-Dist: sphinx
Requires-Dist: myst-parser
Requires-Dist: sphinxcontrib-plantuml
Requires-Dist: sphinxcontrib-mermaid
Provides-Extra: testing
Requires-Dist: setuptools ; extra == 'testing'
Requires-Dist: pytest ; extra == 'testing'
Requires-Dist: pytest-cov ; extra == 'testing'
